pytest_regressions/__init__.py
pytest_regressions/common.py
pytest_regressions/data_regression.py
pytest_regressions/dataframe_regression.py
pytest_regressions/file_regression.py
pytest_regressions/image_regression.py
pytest_regressions/ndarrays_regression.py
pytest_regressions/num_regression.py
pytest_regressions/plugin.py
pytest_regressions/py.typed
pytest_regressions/testing.py
pytest_regressions-2.9.1.dist-info/licenses/LICENSE
pytest_regressions-2.9.1.dist-info/METADATA
pytest_regressions-2.9.1.dist-info/WHEEL
pytest_regressions-2.9.1.dist-info/entry_points.txt
pytest_regressions-2.9.1.dist-info/top_level.txt
pytest_regressions-2.9.1.dist-info/RECORD
