Metadata-Version: 2.4
Name: pytest-regressions
Version: 2.9.1
Summary: Easy to use fixtures to write regression tests.
Home-page: https://github.com/ESSS/pytest-regressions
Author: ESSS
Author-email: foss@esss.co
Maintainer: Bruno Oliveira
Maintainer-email: bruno@esss.co
License: MIT
Classifier: Development Status :: 5 - Production/Stable
Classifier: Framework :: Pytest
Classifier: Intended Audience :: Developers
Classifier: Topic :: Software Development :: Testing
Classifier: Programming Language :: Python :: 3
Classifier: Programming Language :: Python :: 3.10
Classifier: Programming Language :: Python :: 3.11
Classifier: Programming Language :: Python :: 3.12
Classifier: Programming Language :: Python :: 3.13
Classifier: Programming Language :: Python :: 3.14
Classifier: Programming Language :: Python :: Implementation :: CPython
Classifier: Operating System :: OS Independent
Classifier: License :: OSI Approved :: MIT License
Requires-Python: >=3.10
License-File: LICENSE
Requires-Dist: pytest-datadir>=1.7.0
Requires-Dist: pytest>=6.2.0
Requires-Dist: pyyaml
Provides-Extra: dev
Requires-Dist: matplotlib; extra == "dev"
Requires-Dist: mypy; extra == "dev"
Requires-Dist: numpy; extra == "dev"
Requires-Dist: pandas; extra == "dev"
Requires-Dist: pillow; extra == "dev"
Requires-Dist: pyarrow; extra == "dev"
Requires-Dist: pre-commit; extra == "dev"
Requires-Dist: restructuredtext-lint; extra == "dev"
Requires-Dist: tox; extra == "dev"
Provides-Extra: num
Requires-Dist: numpy; extra == "num"
Requires-Dist: pandas; extra == "num"
Provides-Extra: image
Requires-Dist: pillow; extra == "image"
Requires-Dist: numpy; extra == "image"
Provides-Extra: dataframe
Requires-Dist: numpy; extra == "dataframe"
Requires-Dist: pandas; extra == "dataframe"
Dynamic: author
Dynamic: author-email
Dynamic: classifier
Dynamic: description
Dynamic: description-content-type
Dynamic: home-page
Dynamic: license
Dynamic: license-file
Dynamic: maintainer
Dynamic: maintainer-email
Dynamic: provides-extra
Dynamic: requires-dist
Dynamic: requires-python
Dynamic: summary
